{ "compressionlevel":-1,
 "height":18,
 "infinite":false,
 "layers":[
        {
         "data":[11, 11, 11, 11, 11, 11, 11, 1, 2, 3, 11, 11, 11, 11, 11, 11, 11, 11, 11, 11, 11, 11, 11, 11, 11, 11, 11, 11, 11, 11, 11, 11,
            11, 11, 11, 11, 11, 1, 3, 12, 13, 28, 2, 2, 3, 11, 11, 1, 3, 11, 1, 3, 11, 1, 2, 2, 2, 3, 11, 11, 11, 11, 11, 11,
            11, 1, 2, 2, 2, 29, 28, 29, 13, 13, 13, 17, 25, 1, 2, 29, 28, 2, 29, 28, 2, 29, 13, 13, 13, 28, 2, 2, 2, 3, 11, 11,
            1, 29, 13, 13, 13, 13, 58, 13, 13, 13, 13, 28, 2, 29, 13, 13, 13, 13, 13, 13, 57, 13, 13, 68, 13, 13, 13, 13, 59, 28, 3, 11,
            12, 13, 17, 24, 18, 13, 57, 13, 72, 13, 13, 13, 68, 57, 13, 17, 24, 18, 13, 13, 13, 13, 13, 13, 13, 57, 13, 13, 13, 13, 28, 3,
            12, 17, 25, 1, 29, 13, 13, 13, 13, 13, 17, 18, 13, 13, 13, 28, 2, 29, 13, 13, 13, 13, 13, 13, 13, 13, 13, 13, 13, 13, 13, 14,
            12, 14, 1, 29, 13, 17, 18, 13, 13, 17, 25, 12, 13, 13, 17, 18, 13, 13, 17, 24, 18, 13, 13, 17, 24, 24, 18, 13, 13, 13, 13, 14,
            12, 28, 29, 13, 13, 14, 12, 13, 13, 28, 3, 23, 24, 18, 14, 12, 13, 13, 14, 11, 12, 13, 13, 28, 3, 11, 12, 13, 13, 13, 13, 14,
            23, 24, 24, 24, 24, 25, 23, 24, 24, 24, 25, 11, 11, 23, 25, 23, 24, 24, 25, 11, 23, 24, 24, 24, 25, 11, 12, 13, 13, 13, 13, 14,
            11, 11, 11, 11, 11, 11, 11, 11, 11, 11, 11, 11, 11, 11, 11, 11, 11, 11, 11, 11, 11, 11, 11, 11, 11, 11, 12, 13, 13, 13, 13, 14,
            1, 2, 2, 2, 3, 1, 2, 2, 2, 2, 2, 2, 3, 1, 2, 2, 2, 2, 2, 2, 2, 2, 2, 2, 2, 2, 29, 13, 13, 13, 13, 14,
            12, 13, 13, 17, 25, 12, 13, 13, 13, 13, 13, 13, 14, 12, 13, 13, 13, 13, 13, 13, 13, 13, 13, 13, 13, 13, 13, 13, 13, 13, 17, 25,
            12, 13, 17, 25, 1, 29, 13, 13, 13, 13, 13, 13, 14, 23, 18, 13, 13, 13, 13, 13, 13, 13, 13, 67, 13, 13, 13, 13, 13, 17, 25, 11,
            23, 18, 28, 2, 29, 59, 13, 13, 57, 13, 13, 13, 28, 2, 29, 13, 13, 13, 13, 68, 13, 58, 13, 13, 13, 57, 13, 68, 13, 14, 11, 11,
            11, 12, 13, 67, 13, 13, 58, 13, 13, 70, 13, 13, 13, 13, 67, 13, 13, 57, 13, 13, 13, 13, 13, 13, 59, 13, 13, 13, 13, 14, 11, 11,
            11, 23, 18, 13, 70, 13, 13, 13, 59, 13, 17, 24, 18, 70, 13, 17, 18, 13, 17, 24, 24, 24, 24, 18, 13, 17, 24, 18, 17, 25, 11, 11,
            11, 11, 23, 18, 13, 57, 13, 17, 18, 13, 28, 3, 23, 24, 24, 25, 12, 13, 14, 1, 2, 3, 11, 23, 24, 25, 11, 12, 14, 11, 11, 11,
            11, 11, 11, 23, 24, 24, 24, 25, 23, 24, 24, 25, 11, 11, 11, 11, 23, 24, 25, 23, 24, 25, 11, 11, 11, 11, 11, 23, 25, 11, 11, 11],
         "height":18,
         "id":2,
         "name":"Background",
         "opacity":1,
         "type":"tilelayer",
         "visible":true,
         "width":32,
         "x":0,
         "y":0
        }, 
        {
         "draworder":"topdown",
         "id":5,
         "name":"Locations",
         "objects":[
                {
                 "height":0,
                 "id":11,
                 "name":"",
                 "point":true,
                 "rotation":0,
                 "type":"start",
                 "visible":true,
                 "width":0,
                 "x":8.0,
                 "y":152.0
                }, 
                {
                 "height":0,
                 "id":13,
                 "name":"",
                 "point":true,
                 "rotation":0,
                 "type":"end",
                 "visible":true,
                 "width":0,
                 "x":408.0,
                 "y":152.0
                }, 
                {
                 "height":0,
                 "id":16,
                 "name":"",
                 "point":true,
                 "rotation":0,
                 "type":"castle",
                 "visible":true,
                 "width":0,
                 "x":440.0,
                 "y":152.0
                }],
         "opacity":1,
         "type":"objectgroup",
         "visible":true,
         "x":0,
         "y":0
        }],
 "nextlayerid":8,
 "nextobjectid":17,
 "orientation":"orthogonal",
 "renderorder":"right-down",
 "tiledversion":"1.8.5",
 "tileheight":16,
 "tilesets":[
        {
         "columns":11,
         "firstgid":1,
         "image":"grass_water.png",
         "imageheight":112,
         "imagewidth":176,
         "margin":0,
         "name":"grass_water",
         "spacing":0,
         "tilecount":77,
         "tileheight":16,
         "tilewidth":16,
         "wangsets":[
                {
                 "colors":[
                        {
                         "color":"#00ff00",
                         "name":"Water",
                         "probability":1,
                         "tile":10
                        }, 
                        {
                         "color":"#aa0000",
                         "name":"Grass",
                         "probability":1,
                         "tile":-1
                        }],
                 "name":"Terrains",
                 "tile":12,
                 "type":"mixed",
                 "wangtiles":[
                        {
                         "tileid":0,
                         "wangid":[1, 1, 2, 2, 2, 1, 1, 1]
                        }, 
                        {
                         "tileid":1,
                         "wangid":[1, 1, 2, 2, 2, 2, 2, 1]
                        }, 
                        {
                         "tileid":2,
                         "wangid":[1, 1, 1, 1, 2, 2, 2, 1]
                        }, 
                        {
                         "tileid":3,
                         "wangid":[0, 0, 0, 0, 2, 0, 0, 0]
                        }, 
                        {
                         "tileid":4,
                         "wangid":[0, 0, 2, 1, 2, 0, 0, 0]
                        }, 
                        {
                         "tileid":5,
                         "wangid":[0, 0, 2, 1, 2, 2, 2, 0]
                        }, 
                        {
                         "tileid":6,
                         "wangid":[0, 0, 2, 2, 2, 1, 2, 0]
                        }, 
                        {
                         "tileid":7,
                         "wangid":[0, 0, 0, 0, 2, 1, 2, 0]
                        }, 
                        {
                         "tileid":8,
                         "wangid":[1, 1, 0, 1, 0, 1, 0, 1]
                        }, 
                        {
                         "tileid":9,
                         "wangid":[0, 0, 0, 1, 0, 0, 0, 1]
                        }, 
                        {
                         "tileid":10,
                         "wangid":[1, 1, 1, 1, 1, 1, 1, 1]
                        }, 
                        {
                         "tileid":11,
                         "wangid":[2, 2, 2, 2, 2, 1, 1, 1]
                        }, 
                        {
                         "tileid":12,
                         "wangid":[2, 2, 2, 2, 2, 2, 2, 2]
                        }, 
                        {
                         "tileid":13,
                         "wangid":[2, 1, 1, 1, 2, 2, 2, 2]
                        }, 
                        {
                         "tileid":14,
                         "wangid":[2, 0, 0, 0, 2, 0, 0, 0]
                        }, 
                        {
                         "tileid":15,
                         "wangid":[2, 2, 2, 1, 2, 0, 0, 0]
                        }, 
                        {
                         "tileid":16,
                         "wangid":[2, 2, 2, 1, 2, 2, 2, 2]
                        }, 
                        {
                         "tileid":17,
                         "wangid":[2, 2, 2, 2, 2, 1, 2, 2]
                        }, 
                        {
                         "tileid":18,
                         "wangid":[2, 0, 0, 0, 2, 1, 2, 2]
                        }, 
                        {
                         "tileid":19,
                         "wangid":[0, 0, 0, 1, 0, 1, 0, 0]
                        }, 
                        {
                         "tileid":20,
                         "wangid":[0, 1, 0, 0, 0, 1, 0, 0]
                        }, 
                        {
                         "tileid":22,
                         "wangid":[2, 2, 2, 1, 1, 1, 1, 1]
                        }, 
                        {
                         "tileid":23,
                         "wangid":[2, 2, 2, 1, 1, 1, 2, 2]
                        }, 
                        {
                         "tileid":24,
                         "wangid":[2, 1, 1, 1, 1, 1, 2, 2]
                        }, 
                        {
                         "tileid":25,
                         "wangid":[2, 0, 0, 0, 0, 0, 0, 0]
                        }, 
                        {
                         "tileid":26,
                         "wangid":[2, 1, 2, 2, 2, 0, 0, 0]
                        }, 
                        {
                         "tileid":27,
                         "wangid":[2, 1, 2, 2, 2, 2, 2, 2]
                        }, 
                        {
                         "tileid":28,
                         "wangid":[2, 2, 2, 2, 2, 2, 2, 1]
                        }, 
                        {
                         "tileid":29,
                         "wangid":[2, 0, 0, 0, 2, 2, 2, 1]
                        }, 
                        {
                         "tileid":30,
                         "wangid":[0, 1, 0, 0, 0, 0, 0, 1]
                        }, 
                        {
                         "tileid":31,
                         "wangid":[0, 1, 0, 0, 0, 1, 0, 1]
                        }, 
                        {
                         "tileid":32,
                         "wangid":[0, 1, 0, 1, 0, 0, 0, 1]
                        },
                    
                        {
                         "tileid":33,
                         "wangid":[0, 0, 2, 0, 0, 0, 0, 0]
                        }, 
                        {
                         "tileid":34,
                         "wangid":[0, 0, 2, 0, 0, 0, 2, 0]
                        }, 
                        {
                         "tileid":35,
                         "wangid":[0, 0, 0, 0, 0, 0, 2, 0]
                        }, 
                        {
                         "tileid":37,
                         "wangid":[2, 1, 2, 0, 0, 0, 0, 0]
                        }, 
                        {
                         "tileid":38,
                         "wangid":[2, 1, 2, 0, 0, 0, 2, 2]
                        }, 
                        {
                         "tileid":39,
                         "wangid":[2, 2, 2, 0, 0, 0, 2, 1]
                        }, 
                        {
                         "tileid":40,
                         "wangid":[2, 0, 0, 0, 0, 0, 2, 1]
                        }, 
                        {
                         "tileid":41,
                         "wangid":[0, 1, 0, 1, 1, 1, 0, 1]
                        }, 
                        {
                         "tileid":42,
                         "wangid":[0, 0, 0, 1, 0, 1, 0, 1]
                        }, 
                        {
                         "tileid":43,
                         "wangid":[0, 1, 0, 1, 0, 1, 0, 0]
                        }, 
                        {
                         "tileid":52,
                         "wangid":[0, 1, 0, 1, 0, 1, 0, 1]
                        }, 
                        {
                         "tileid":53,
                         "wangid":[0, 1, 0, 1, 0, 1, 0, 1]
                        }]
                }, 
                {
                 "colors":[
                        {
                         "color":"#ff0000",
                         "name":"Grass",
                         "probability":1,
                         "tile":12
                        }, 
                        {
                         "color":"#00ff00",
                         "name":"Water",
                         "probability":1,
                         "tile":10
                        }],
                 "name":"TTT",
                 "tile":-1,
                 "type":"corner",
                 "wangtiles":[
                        {
                         "tileid":0,
                         "wangid":[0, 2, 0, 1, 0, 2, 0, 2]
                        }, 
                        {
                         "tileid":1,
                         "wangid":[0, 2, 0, 1, 0, 1, 0, 2]
                        }, 
                        {
                         "tileid":2,
                         "wangid":[0, 2, 0, 2, 0, 1, 0, 2]
                        }, 
                        {
                         "tileid":4,
                         "wangid":[0, 0, 0, 2, 0, 0, 0, 0]
                        }, 
                        {
                         "tileid":5,
                         "wangid":[0, 0, 0, 2, 0, 0, 0, 0]
                        }, 
                        {
                         "tileid":6,
                         "wangid":[0, 0, 0, 0, 0, 2, 0, 0]
                        }, 
                        {
                         "tileid":7,
                         "wangid":[0, 0, 0, 0, 0, 2, 0, 0]
                        }, 
                        {
                         "tileid":10,
                         "wangid":[0, 2, 0, 2, 0, 2, 0, 2]
                        }, 
                        {
                         "tileid":11,
                         "wangid":[0, 1, 0, 1, 0, 2, 0, 2]
                        }, 
                        {
                         "tileid":12,
                         "wangid":[0, 1, 0, 1, 0, 1, 0, 1]
                        }, 
                        {
                         "tileid":13,
                         "wangid":[0, 2, 0, 2, 0, 1, 0, 1]
                        }, 
                        {
                         "tileid":15,
                         "wangid":[0, 0, 0, 2, 0, 0, 0, 0]
                        }, 
                        {
                         "tileid":16,
                         "wangid":[0, 1, 0, 2, 0, 1, 0, 1]
                        }, 
                        {
                         "tileid":17,
                         "wangid":[0, 1, 0, 1, 0, 2, 0, 1]
                        }, 
                        {
                         "tileid":18,
                         "wangid":[0, 0, 0, 0, 0, 2, 0, 0]
                        }, 
                        {
                         "tileid":22,
                         "wangid":[0, 1, 0, 2, 0, 2, 0, 2]
                        }, 
                        {
                         "tileid":23,
                         "wangid":[0, 1, 0, 2, 0, 2, 0, 1]
                        }, 
                        {
                         "tileid":24,
                         "wangid":[0, 2, 0, 2, 0, 2, 0, 1]
                        }, 
                        {
                         "tileid":26,
                         "wangid":[0, 2, 0, 0, 0, 0, 0, 0]
                        }, 
                        {
                         "tileid":27,
                         "wangid":[0, 2, 0, 1, 0, 1, 0, 1]
                        }, 
                        {
                         "tileid":28,
                         "wangid":[0, 1, 0, 1, 0, 1, 0, 2]
                        }, 
                        {
                         "tileid":29,
                         "wangid":[0, 0, 0, 0, 0, 0, 0, 2]
                        }, 
                        {
                         "tileid":37,
                         "wangid":[0, 2, 0, 0, 0, 0, 0, 0]
                        }, 
                        {
                         "tileid":38,
                         "wangid":[0, 2, 0, 0, 0, 0, 0, 0]
                        }, 
                        {
                         "tileid":39,
                         "wangid":[0, 0, 0, 0, 0, 0, 0, 2]
                        }, 
                        {
                         "tileid":40,
                         "wangid":[0, 0, 0, 0, 0, 0, 0, 2]
                        }]
                }]
        }],
 "tilewidth":16,
 "type":"map",
 "version":"1.8",
 "width":32
}